qcombo/__init__.py
qcombo/__main__.py
qcombo/canonical.py
qcombo/output.py
qcombo/simplify.py
qcombo/tools.py
qcombo/wickcaculate.py
qcombo-0.1.4.dist-info/licenses/LICENSE
qcombo-0.1.4.dist-info/METADATA
qcombo-0.1.4.dist-info/WHEEL
qcombo-0.1.4.dist-info/entry_points.txt
qcombo-0.1.4.dist-info/top_level.txt
qcombo-0.1.4.dist-info/RECORD
